MANIFEST.in
README.rst
setup.cfg
setup.py
collective/__init__.py
collective.typecriterion.egg-info/PKG-INFO
collective.typecriterion.egg-info/SOURCES.txt
collective.typecriterion.egg-info/dependency_links.txt
collective.typecriterion.egg-info/entry_points.txt
collective.typecriterion.egg-info/namespace_packages.txt
collective.typecriterion.egg-info/not-zip-safe
collective.typecriterion.egg-info/requires.txt
collective.typecriterion.egg-info/top_level.txt
collective/typecriterion/__init__.py
collective/typecriterion/configure.zcml
collective/typecriterion/index_modifier.py
collective/typecriterion/interfaces.py
collective/typecriterion/persistent.py
collective/typecriterion/testing.py
collective/typecriterion/vocabularies.py
collective/typecriterion/Extensions/install.py
collective/typecriterion/browser/__init__.py
collective/typecriterion/browser/configure.zcml
collective/typecriterion/browser/controlpanel.py
collective/typecriterion/browser/resources/types.png
collective/typecriterion/locales/collective.typecriterion-manual.pot
collective/typecriterion/locales/collective.typecriterion.pot
collective/typecriterion/locales/rebuildPo.sh
collective/typecriterion/locales/it/LC_MESSAGES/collective.typecriterion.mo
collective/typecriterion/locales/it/LC_MESSAGES/collective.typecriterion.po
collective/typecriterion/profiles/default/browserlayer.xml
collective/typecriterion/profiles/default/controlpanel.xml
collective/typecriterion/profiles/default/metadata.xml
collective/typecriterion/profiles/default/registry.xml
collective/typecriterion/profiles/default/rolemap.xml
collective/typecriterion/profiles/uninstall/browserlayer.xml
collective/typecriterion/profiles/uninstall/controlpanel.xml
collective/typecriterion/profiles/uninstall/registry.xml
collective/typecriterion/tests/__init__.py
collective/typecriterion/tests/test_query.py
docs/HISTORY.txt
docs/INSTALL.txt
docs/LICENSE.GPL
docs/LICENSE.rst