Metadata-Version: 1.1
Name: collective.typecriterion
Version: 0.1.0
Summary: A new, more flexible, content type criterion for Plone collections
Home-page: https://github.com/keul/collective.typecriterion
Author: keul
Author-email: luca@keul.it
License: GPL
Keywords: plone criterion collection type
Platform: UNKNOWN
Classifier: Development Status :: 4 - Beta
Classifier: Framework :: Plone
Classifier: Framework :: Plone :: 4.3
Classifier: Programming Language :: Python
